Metadata-Version: 1.0
Name: python-skew-correction
Version: 1.3
Summary: Python Text Image Skew Correction
Home-page: https://github.com/fatihsucu/python-skew-correction
Author: Fatih Sucu
Author-email: fatihsucu0@gmail.com
License: MIT
Platform: UNKNOWN
